LICENSE
MANIFEST.in
README.md
setup.cfg
setup.py
happie/__init__.py
happie/_version.py
happie/happie.py
happie/install.py
happie/parsers.py
happie/plot_gbk.py
happie/runners.py
happie/shared_methods.py
happie/test_happie.py
happie.egg-info/PKG-INFO
happie.egg-info/SOURCES.txt
happie.egg-info/dependency_links.txt
happie.egg-info/entry_points.txt
happie.egg-info/requires.txt
happie.egg-info/top_level.txt